{
    "uuid": [
        {
            "value": "edfab133-7050-4ad8-8afb-2ed2b0fd51e0"
        }
    ],
    "langcode": [
        {
            "value": "es"
        }
    ],
    "bundle": [
        {
            "target_id": "image",
            "target_type": "media_type",
            "target_uuid": "bae7fb4d-3795-4d25-ab96-3af36b14586f"
        }
    ],
    "revision_created": [
        {
            "value": "2025-07-04T03:58:40+00:00",
            "format": "Y-m-d\\TH:i:sP"
        }
    ],
    "revision_user": [
        {
            "target_type": "user",
            "target_uuid": "fbb7bd43-6d18-4519-b11a-b47733d71451"
        }
    ],
    "revision_log_message": [],
    "status": [
        {
            "value": true
        }
    ],
    "uid": [
        {
            "target_type": "user",
            "target_uuid": "fbb7bd43-6d18-4519-b11a-b47733d71451"
        }
    ],
    "name": [
        {
            "value": "photo_sesiones.jpg"
        }
    ],
    "thumbnail": [
        {
            "alt": "Estudios",
            "title": null,
            "width": 6000,
            "height": 4000,
            "target_type": "file",
            "target_uuid": "9b94b8f9-8910-4834-b48a-37a70b500ecc"
        }
    ],
    "created": [
        {
            "value": "2025-06-30T13:30:39+00:00",
            "format": "Y-m-d\\TH:i:sP"
        }
    ],
    "changed": [
        {
            "value": "2025-07-04T03:58:40+00:00",
            "format": "Y-m-d\\TH:i:sP"
        }
    ],
    "default_langcode": [
        {
            "value": true
        }
    ],
    "revision_translation_affected": [
        {
            "value": true
        }
    ],
    "path": [
        {
            "alias": "",
            "pid": null,
            "langcode": "es"
        }
    ],
    "field_filmstrip_link": [
        {
            "uri": "internal:\/foto\/sesiones",
            "title": "Sesiones",
            "options": []
        }
    ],
    "field_media_image": [
        {
            "alt": "Estudios",
            "title": "",
            "width": 6000,
            "height": 4000,
            "target_type": "file",
            "target_uuid": "9b94b8f9-8910-4834-b48a-37a70b500ecc"
        }
    ]
}